neon_phal_plugin_linear_led/__init__.py
neon_phal_plugin_linear_led/neopixel_led.py
neon_phal_plugin_linear_led/smbus_led.py
neon_phal_plugin_linear_led-0.2.4.dist-info/LICENSE.md
neon_phal_plugin_linear_led-0.2.4.dist-info/METADATA
neon_phal_plugin_linear_led-0.2.4.dist-info/WHEEL
neon_phal_plugin_linear_led-0.2.4.dist-info/entry_points.txt
neon_phal_plugin_linear_led-0.2.4.dist-info/top_level.txt
neon_phal_plugin_linear_led-0.2.4.dist-info/RECORD
