Metadata-Version: 2.1
Name: neon-phal-plugin-linear-led
Version: 0.2.4
Summary: Linear/Ring LED Interface
Home-page: https://github.com/NeonGeckoCom/neon-phal-plugin-linear_led
Author: Neongecko
Author-email: developers@neon.ai
License: BSD-3
License-File: LICENSE.md
Requires-Dist: sj201-interface~=0.1
Requires-Dist: ovos-plugin-manager>=0.0.21,~=0.0
Requires-Dist: ovos-utils>=0.0.26,~=0.0
Requires-Dist: ovos-bus-client>=0.0.3,~=0.0
